azure/mgmt/redisenterprise/__init__.py
azure/mgmt/redisenterprise/_configuration.py
azure/mgmt/redisenterprise/_patch.py
azure/mgmt/redisenterprise/_redis_enterprise_management_client.py
azure/mgmt/redisenterprise/_version.py
azure/mgmt/redisenterprise/py.typed
azure/mgmt/redisenterprise/_utils/__init__.py
azure/mgmt/redisenterprise/_utils/serialization.py
azure/mgmt/redisenterprise/aio/__init__.py
azure/mgmt/redisenterprise/aio/_configuration.py
azure/mgmt/redisenterprise/aio/_patch.py
azure/mgmt/redisenterprise/aio/_redis_enterprise_management_client.py
azure/mgmt/redisenterprise/aio/operations/__init__.py
azure/mgmt/redisenterprise/aio/operations/_access_policy_assignment_operations.py
azure/mgmt/redisenterprise/aio/operations/_databases_operations.py
azure/mgmt/redisenterprise/aio/operations/_operations.py
azure/mgmt/redisenterprise/aio/operations/_operations_status_operations.py
azure/mgmt/redisenterprise/aio/operations/_patch.py
azure/mgmt/redisenterprise/aio/operations/_private_endpoint_connections_operations.py
azure/mgmt/redisenterprise/aio/operations/_private_link_resources_operations.py
azure/mgmt/redisenterprise/aio/operations/_redis_enterprise_operations.py
azure/mgmt/redisenterprise/models/__init__.py
azure/mgmt/redisenterprise/models/_models_py3.py
azure/mgmt/redisenterprise/models/_patch.py
azure/mgmt/redisenterprise/models/_redis_enterprise_management_client_enums.py
azure/mgmt/redisenterprise/operations/__init__.py
azure/mgmt/redisenterprise/operations/_access_policy_assignment_operations.py
azure/mgmt/redisenterprise/operations/_databases_operations.py
azure/mgmt/redisenterprise/operations/_operations.py
azure/mgmt/redisenterprise/operations/_operations_status_operations.py
azure/mgmt/redisenterprise/operations/_patch.py
azure/mgmt/redisenterprise/operations/_private_endpoint_connections_operations.py
azure/mgmt/redisenterprise/operations/_private_link_resources_operations.py
azure/mgmt/redisenterprise/operations/_redis_enterprise_operations.py
azure_mgmt_redisenterprise-3.1.0.dist-info/licenses/LICENSE
azure_mgmt_redisenterprise-3.1.0.dist-info/METADATA
azure_mgmt_redisenterprise-3.1.0.dist-info/WHEEL
azure_mgmt_redisenterprise-3.1.0.dist-info/top_level.txt
azure_mgmt_redisenterprise-3.1.0.dist-info/RECORD
